pibooth_date_folder.py
pibooth_date_folder-1.5.9.dist-info/licenses/LICENSE
pibooth_date_folder-1.5.9.dist-info/METADATA
pibooth_date_folder-1.5.9.dist-info/WHEEL
pibooth_date_folder-1.5.9.dist-info/entry_points.txt
pibooth_date_folder-1.5.9.dist-info/top_level.txt
pibooth_date_folder-1.5.9.dist-info/RECORD
