Metadata-Version: 2.4
Name: pibooth-date-folder
Version: 1.5.9
Summary: PiBooth plugin to split/save sessions into date-based folders with an optional daily time threshold.
Home-page: https://github.com/DJ-Dingo/pibooth-date-folder
Author: Kenneth Nicholas Jørgensen
Author-email: 
License: GPL-3.0-or-later
Project-URL: Homepage, https://github.com/DJ-Dingo/pibooth-date-folder
Project-URL: Repository, https://github.com/DJ-Dingo/pibooth-date-folder
Project-URL: Issues, https://github.com/DJ-Dingo/pibooth-date-folder/issues
Keywords: pibooth,pibooth plugin,plugin,photobooth,selfiecam,raspberry,raspberry pi,date,folder,sessions,organize,camera,kiosk,Raspberry Pi OS,python
Classifier: Programming Language :: Python :: 3
Classifier: Programming Language :: Python :: 3.6
Classifier: Programming Language :: Python :: 3.7
Classifier: Programming Language :: Python :: 3.8
Classifier: Programming Language :: Python :: 3.9
Classifier: Programming Language :: Python :: 3.10
Classifier: Programming Language :: Python :: 3.11
Classifier: Programming Language :: Python :: 3.12
Classifier: Programming Language :: Python :: 3 :: Only
Classifier: License :: OSI Approved :: GNU General Public License v3 or later (GPLv3+)
Classifier: Operating System :: OS Independent
Classifier: Topic :: Multimedia :: Graphics
Classifier: Topic :: Software Development :: Libraries :: Python Modules
Requires-Python: >=3.6
License-File: LICENSE
Requires-Dist: pibooth>=2.0.8
Dynamic: author
Dynamic: classifier
Dynamic: description
Dynamic: description-content-type
Dynamic: home-page
Dynamic: keywords
Dynamic: license
Dynamic: license-file
Dynamic: project-url
Dynamic: requires-dist
Dynamic: requires-python
Dynamic: summary
